rocketHibou/__init__.py
rocketHibou/rocketHibou.py
rocketHibou-1.0.0.dist-info/LICENSE.txt
rocketHibou-1.0.0.dist-info/METADATA
rocketHibou-1.0.0.dist-info/WHEEL
rocketHibou-1.0.0.dist-info/top_level.txt
rocketHibou-1.0.0.dist-info/RECORD
